[{"count": 71707, "_id": "Harbor"}, {"count": 58305, "_id": "Hollenbeck"}, {"count": 67789, "_id": "Rampart"}, {"count": 68621, "_id": "West Valley"}, {"count": 87365, "_id": "North Hollywood"}, {"count": 64358, "_id": "Wilshire"}, {"count": 74191, "_id": "Topanga"}, {"count": 103422, "_id": "Southwest"}, {"count": 76404, "_id": "Van Nuys"}, {"count": 74833, "_id": "Devonshire"}, {"count": 84511, "_id": "Southeast"}, {"count": 111850, "_id": "77th Street"}, {"count": 67087, "_id": "West Los Angeles"}, {"count": 84790, "_id": "Pacific"}, {"count": 75283, "_id": "Newton"}, {"count": 68056, "_id": "Central"}, {"count": 77422, "_id": "Northeast"}, {"count": 61617, "_id": "Foothill"}, {"count": 73161, "_id": "Hollywood"}, {"count": 71054, "_id": "Olympic"}, {"count": 81071, "_id": "Mission"}]